CHANGES
COPYING.LGPLv3
LICENSE
MANIFEST.in
README
ez_setup.py
requirements.txt
setup.py
bundledmedia/__init__.py
bundledmedia/datastructures.py
bundledmedia/middleware.py
bundledmedia/models.py
bundledmedia/templatetags/__init__.py
bundledmedia/templatetags/bundledmedia.py
django_bundledmedia.egg-info/PKG-INFO
django_bundledmedia.egg-info/SOURCES.txt
django_bundledmedia.egg-info/dependency_links.txt
django_bundledmedia.egg-info/requires.txt
django_bundledmedia.egg-info/top_level.txt